noworkflow_labextension/__init__.py
noworkflow_labextension/_version.py
noworkflow_labextension-0.1.0.data/data/share/jupyter/labextensions/@noworkflow/labextension/build_log.json
noworkflow_labextension-0.1.0.data/data/share/jupyter/labextensions/@noworkflow/labextension/package.json
noworkflow_labextension-0.1.0.data/data/share/jupyter/labextensions/@noworkflow/labextension/static/history_lib_index_js.30324db95c3d6bbbec44.js
noworkflow_labextension-0.1.0.data/data/share/jupyter/labextensions/@noworkflow/labextension/static/history_lib_index_js.30324db95c3d6bbbec44.js.map
noworkflow_labextension-0.1.0.data/data/share/jupyter/labextensions/@noworkflow/labextension/static/lib_index_js.cc08504316485c558298.js
noworkflow_labextension-0.1.0.data/data/share/jupyter/labextensions/@noworkflow/labextension/static/lib_index_js.cc08504316485c558298.js.map
noworkflow_labextension-0.1.0.data/data/share/jupyter/labextensions/@noworkflow/labextension/static/node_modules_jupyterlab_builder_node_modules_css-loader_dist_cjs_js_style_base_css-node_modul-3a2825.b797888c2bad8d4edc96.js
noworkflow_labextension-0.1.0.data/data/share/jupyter/labextensions/@noworkflow/labextension/static/node_modules_jupyterlab_builder_node_modules_css-loader_dist_cjs_js_style_base_css-node_modul-3a2825.b797888c2bad8d4edc96.js.map
noworkflow_labextension-0.1.0.data/data/share/jupyter/labextensions/@noworkflow/labextension/static/remoteEntry.3544740e870ee5a2dc8b.js
noworkflow_labextension-0.1.0.data/data/share/jupyter/labextensions/@noworkflow/labextension/static/remoteEntry.3544740e870ee5a2dc8b.js.map
noworkflow_labextension-0.1.0.data/data/share/jupyter/labextensions/@noworkflow/labextension/static/style.js
noworkflow_labextension-0.1.0.data/data/share/jupyter/labextensions/@noworkflow/labextension/static/style_index_js.1172bd7deac27a64f1cf.js
noworkflow_labextension-0.1.0.data/data/share/jupyter/labextensions/@noworkflow/labextension/static/style_index_js.1172bd7deac27a64f1cf.js.map
noworkflow_labextension-0.1.0.dist-info/METADATA
noworkflow_labextension-0.1.0.dist-info/WHEEL
noworkflow_labextension-0.1.0.dist-info/licenses/LICENSE
noworkflow_labextension-0.1.0.dist-info/RECORD
