Metadata-Version: 2.3
Name: noworkflow_labextension
Version: 0.1.0
Summary: A JupyterLab extension for noWorkflow
Project-URL: Homepage, https://github.com/gems-uff/noworkflow
Project-URL: Bug Tracker, https://github.com/gems-uff/noworkflow/issues
Project-URL: Repository, https://github.com/gems-uff/noworkflow.git
Author-email: Joao Felipe Pimentel <joaofelipenp@gmail.com>
License: The MIT License (MIT)
License-File: LICENSE
Keywords: jupyter,jupyterlab,jupyterlab-extension
Classifier: Framework :: Jupyter
Classifier: Framework :: Jupyter :: JupyterLab
Classifier: Framework :: Jupyter :: JupyterLab :: 4
Classifier: Framework :: Jupyter :: JupyterLab :: Extensions
Classifier: Framework :: Jupyter :: JupyterLab :: Extensions :: Prebuilt
Classifier: License :: OSI Approved :: BSD License
Classifier: Programming Language :: Python
Classifier: Programming Language :: Python :: 3
Classifier: Programming Language :: Python :: 3.8
Classifier: Programming Language :: Python :: 3.9
Classifier: Programming Language :: Python :: 3.10
Classifier: Programming Language :: Python :: 3.11
Classifier: Programming Language :: Python :: 3.12
Requires-Python: >=3.8
